py_file_versioning/__init__.py
py_file_versioning/file_versioning.py
py_file_versioning/pyfileversioning.py
py_file_versioning/test_file_versioning.py
py_file_versioning-0.9.1.dist-info/METADATA
py_file_versioning-0.9.1.dist-info/WHEEL
py_file_versioning-0.9.1.dist-info/entry_points.txt
py_file_versioning-0.9.1.dist-info/licenses/LICENSE
py_file_versioning-0.9.1.dist-info/RECORD
