Metadata-Version: 2.4
Name: py-file-versioning
Version: 0.9.1
Summary: A flexible file versioning system with compression support
Project-URL: Homepage, https://github.com/jftuga/py-file-versioning
Project-URL: Repository, https://github.com/jftuga/py-file-versioning.git
Project-URL: Issues, https://github.com/jftuga/py-file-versioning/issues
Author-email: John Taylor <jftuga@users.noreply.github.com>
License: MIT License
License-File: LICENSE
Keywords: backup,file-backup,file-history,file-management,version-control,versioning
Classifier: Development Status :: 4 - Beta
Classifier: Intended Audience :: Developers
Classifier: Intended Audience :: System Administrators
Classifier: License :: OSI Approved :: MIT License
Classifier: Operating System :: OS Independent
Classifier: Programming Language :: Python :: 3
Classifier: Programming Language :: Python :: 3.10
Classifier: Programming Language :: Python :: 3.11
Classifier: Programming Language :: Python :: 3.12
Classifier: Topic :: System :: Archiving :: Backup
Classifier: Topic :: System :: Systems Administration
Classifier: Topic :: Utilities
Requires-Python: >=3.10
Provides-Extra: dev
Requires-Dist: black>=24.1.0; extra == 'dev'
Requires-Dist: build>=1.0.3; extra == 'dev'
Requires-Dist: flake8>=7.0.0; extra == 'dev'
Requires-Dist: isort>=5.13.0; extra == 'dev'
Requires-Dist: pytest-cov>=4.1.0; extra == 'dev'
Requires-Dist: pytest>=7.0.0; extra == 'dev'
Requires-Dist: ruff>=0.9.2; extra == 'dev'
Requires-Dist: twine>=4.0.2; extra == 'dev'
